python_twitch_irc/__init__.py
python_twitch_irc/irc.py
python_twitch_irc-1.1.0.dist-info/METADATA
python_twitch_irc-1.1.0.dist-info/RECORD
python_twitch_irc-1.1.0.dist-info/WHEEL
python_twitch_irc-1.1.0.dist-info/entry_points.txt
python_twitch_irc-1.1.0.dist-info/top_level.txt
