Metadata-Version: 2.1
Name: python-twitch-irc
Version: 1.1.0
Summary: Python Library for Twitch IRC eccentricities
Home-page: https://github.com/jspaulsen/python-twitch-irc
Author: jspaulsen
Author-email: jspaulsen@github.com
License: UNKNOWN
Platform: UNKNOWN
Classifier: Programming Language :: Python :: 3.6
Classifier: Development Status :: 4 - Beta
Classifier: License :: OSI Approved :: MIT License
Classifier: Operating System :: OS Independent
